gada_pyrunner/__init__.py
gada_pyrunner/__version__.py
gada_pyrunner/pymodule.py
gada_pyrunner/python.py
gada_pyrunner/test_utils.py
test/__init__.py
test/test_pymodule.py
test/test_python.py
test/utils.py
test/testnodes/__init__.py
gada_pyrunner-0.4a0.dist-info/LICENSE
gada_pyrunner-0.4a0.dist-info/METADATA
gada_pyrunner-0.4a0.dist-info/WHEEL
gada_pyrunner-0.4a0.dist-info/entry_points.txt
gada_pyrunner-0.4a0.dist-info/top_level.txt
gada_pyrunner-0.4a0.dist-info/zip-safe
gada_pyrunner-0.4a0.dist-info/RECORD
