Metadata-Version: 2.1
Name: gada-pyrunner
Version: 0.4a0
Summary: Python runner for gada
Home-page: https://github.com/gadalang/gada-pyrunner
Author: Jeremy Morosi
Author-email: jeremymorosi@hotmail.com
License: UNKNOWN
Project-URL: Bug Tracker, https://github.com/gadalang/gada-pyrunner/issues
Project-URL: Source Code, https://github.com/gadalang/gada-pyrunner/
Platform: UNKNOWN
Classifier: Development Status :: 3 - Alpha
Classifier: Intended Audience :: Developers
Classifier: Topic :: Software Development :: Build Tools
Classifier: Programming Language :: Python :: 3.7
Classifier: Programming Language :: Python :: 3.8
Classifier: Programming Language :: Python :: 3.9
Requires-Python: >=3.7
Requires-Dist: gada
